{
    "url": "/transactions/changing-a-transactions-category/",
    "title": "Change A Transactions Category",
    "subcategoryPresent": false,
    "breadcrumb": [
        {
            "crumbTitle": "Help Center",
            "crumbUrl": "/"
		},
        {
            "crumbTitle": "Transactions",
            "crumbUrl": "/transactions/"
		}
	],
    "content": [
        {
            "tag": "p",
            "html": "You'll want to explore your options and find a category for every transaction to fit into. Sometimes, the already added transactions would have to be modified."
		},
        {
            "tag": "img",
            "classInfo": "article-image",
            "srcUrl": "/img/transactions/change-category.gif"
		},
        {
            "tag": "div",
            "classInfo": "item-container",
            "html": "<div class=\"icon\">1</div><div class=\"copy-container\"><p class=\"description mb-3\">Click and Drag the transactions.</p></div>"
		},
        {
            "tag": "div",
            "classInfo": "item-container",
            "html": "<div class=\"icon\">2</div><div class=\"copy-container\"><p class=\"description mb-3\">Drop the transactions below the relevant category.</p></div>"
		}
	]
}
