{
    "url": "/transactions/how-to-delete-a-category/",
    "title": "Comment supprimer une catégorie",
    "subcategoryPresent": false,
    "breadcrumb": [
        {
            "crumbTitle": "Centre d'aide",
            "crumbUrl": "/"
		},
        {
            "crumbTitle": "Transactions",
            "crumbUrl": "/transactions/"
		}
	],
    "content": [
        {
            "tag": "p",
            "html": "La suppression d'une catégorie, supprime également toutes les opérations associées à la date sélectionnée ainsi que le budget qui lui est associé."
		},
        {
            "tag": "img",
            "classInfo": "article-image",
            "srcUrl": "/img/transactions/delete-category.gif"
		},
        {
            "tag": "div",
            "classInfo": "item-container",
            "html": "<div class=\"icon\">1</div><div class=\"copy-container\"><p class=\"description mb-3\">Toutes vos transactions associées à la catégorie pour le mois sélectionné seront supprimées.</p></div>"
		},
        {
            "tag": "div",
            "classInfo": "item-container",
            "html": "<div class=\"icon\">2</div><div class=\"copy-container\"><p class=\"description mb-3\">Le budget associé à la catégorie sera également supprimé.</p></div>"
		},
        {
            "tag": "div",
            "classInfo": "item-container",
            "html": "<div class=\"icon\">2</div><div class=\"copy-container\"><p class=\"description mb-3\">La catégorie en question sera également supprimée.</p></div>"
		}
	]
}
